LICENSE
ast_selector/__init__.py
ast_selector/exceptions.py
ast_selector/main.py
ast_selector/selectors.py
ast_selector-0.2.0.dist-info/LICENSE
ast_selector-0.2.0.dist-info/WHEEL
ast_selector-0.2.0.dist-info/METADATA
ast_selector-0.2.0.dist-info/RECORD
